KivyZhongwenBianchengZhinan/README.md
KivyZhongwenBianchengZhinan/__init__.py
KivyZhongwenBianchengZhinan/__main__.py
KivyZhongwenBianchengZhinan/file.epub
KivyZhongwenBianchengZhinan/index.html
KivyZhongwenBianchengZhinan/css/__init__.py
KivyZhongwenBianchengZhinan/css/annotations.css
KivyZhongwenBianchengZhinan/css/main.css
KivyZhongwenBianchengZhinan/css/normalize.css
KivyZhongwenBianchengZhinan/css/popup.css
KivyZhongwenBianchengZhinan/font/__init__.py
KivyZhongwenBianchengZhinan/font/fontello.eot
KivyZhongwenBianchengZhinan/font/fontello.svg
KivyZhongwenBianchengZhinan/font/fontello.ttf
KivyZhongwenBianchengZhinan/font/fontello.woff
KivyZhongwenBianchengZhinan/img/__init__.py
KivyZhongwenBianchengZhinan/img/annotator-glyph-sprite.png
KivyZhongwenBianchengZhinan/img/annotator-icon-sprite.png
KivyZhongwenBianchengZhinan/img/apple-touch-icon.png
KivyZhongwenBianchengZhinan/img/cancelfullscreen.png
KivyZhongwenBianchengZhinan/img/close.png
KivyZhongwenBianchengZhinan/img/fullscreen.png
KivyZhongwenBianchengZhinan/img/loader.gif
KivyZhongwenBianchengZhinan/img/menu-icon.png
KivyZhongwenBianchengZhinan/img/save.png
KivyZhongwenBianchengZhinan/img/saved.png
KivyZhongwenBianchengZhinan/img/settings-s.png
KivyZhongwenBianchengZhinan/img/settings.png
KivyZhongwenBianchengZhinan/img/star.png
KivyZhongwenBianchengZhinan/js/__init__.py
KivyZhongwenBianchengZhinan/js/epub.js
KivyZhongwenBianchengZhinan/js/epub.min.js
KivyZhongwenBianchengZhinan/js/epub.min.map
KivyZhongwenBianchengZhinan/js/hooks.min.js
KivyZhongwenBianchengZhinan/js/hooks.min.map
KivyZhongwenBianchengZhinan/js/reader.js
KivyZhongwenBianchengZhinan/js/reader.js.map
KivyZhongwenBianchengZhinan/js/reader.min.js
KivyZhongwenBianchengZhinan/js/reader.min.map
KivyZhongwenBianchengZhinan/js/hooks/__init__.py
KivyZhongwenBianchengZhinan/js/hooks/extensions/__init__.py
KivyZhongwenBianchengZhinan/js/hooks/extensions/highlight.js
KivyZhongwenBianchengZhinan/js/libs/__init__.py
kivy_zhongwen_biancheng_zhinan-2024.3.3.0.dist-info/METADATA
kivy_zhongwen_biancheng_zhinan-2024.3.3.0.dist-info/WHEEL
kivy_zhongwen_biancheng_zhinan-2024.3.3.0.dist-info/entry_points.txt
kivy_zhongwen_biancheng_zhinan-2024.3.3.0.dist-info/top_level.txt
kivy_zhongwen_biancheng_zhinan-2024.3.3.0.dist-info/RECORD
